study_quiz_cli/__init__.py
study_quiz_cli/__main__.py
study_quiz_cli-0.1.2.dist-info/LICENSE
study_quiz_cli-0.1.2.dist-info/METADATA
study_quiz_cli-0.1.2.dist-info/WHEEL
study_quiz_cli-0.1.2.dist-info/entry_points.txt
study_quiz_cli-0.1.2.dist-info/RECORD
