Metadata-Version: 2.1
Name: study-quiz-cli
Version: 0.1.2
Summary: A command-line study quiz game where users write and answer their own multiple-choice questions to self-test and track their scores.
Author: DavidTJGriffin
Author-email: david.dtjg2001@gmail.com
Requires-Python: >=3.12,<4.0
Classifier: License :: OSI Approved :: MIT License
Classifier: Programming Language :: Python :: 3
Classifier: Programming Language :: Python :: 3.12
